iremd_k/__init__.py
iremd_k/my_codes.py
iremd_k-0.0.1.dist-info/LICENSE.txt
iremd_k-0.0.1.dist-info/METADATA
iremd_k-0.0.1.dist-info/WHEEL
iremd_k-0.0.1.dist-info/top_level.txt
iremd_k-0.0.1.dist-info/RECORD
